subtratorcompleto.v
// subtratorcompleto.v
module subtratorcompleto (a, b, cin, s, cout);
    input a, b, cin;     // Entradas
    output s, cout;      // Saídas

    // Lógica do Subtrator Completo
    assign s    = a ^ b ^ cin;               // Diferença
    assign cout = (~a & b) | ((~(a ^ b)) & cin); // Empréstimo (Borrow)
endmodule

subtratorcompleto_tb.v
// subtratorcompleto_tb.v
`timescale 1ns/1ps
`include "subtratorcompleto.v"

module subtratorcompleto_tb;
    reg a, b, cin;       // Entradas de teste
    wire s, cout;        // Saídas observadas

    // Instancia o módulo principal
    subtratorcompleto uut (.a(a), .b(b), .cin(cin), .s(s), .cout(cout));

    initial begin
        // Configura o arquivo para GTKWave
        $dumpfile("subtratorcompleto.vcd");
        $dumpvars(0, subtratorcompleto_tb);

        // Testa todas as combinações possíveis (tabela verdade)
        a=0; b=0; cin=0; #10;
        a=0; b=0; cin=1; #10;
        a=0; b=1; cin=0; #10;
        a=0; b=1; cin=1; #10;
        a=1; b=0; cin=0; #10;
        a=1; b=0; cin=1; #10;
        a=1; b=1; cin=0; #10;
        a=1; b=1; cin=1; #10;

        $finish;
    end
endmodule

subtratorcompleto.vcd
$date
	Sun Sep 07 23:03:30 2025
$end
$version
	Icarus Verilog
$end
$timescale
	1ps
$end
$scope module subtratorcompleto_tb $end
$var wire 1 ! s $end
$var wire 1 " cout $end
$var reg 1 # a $end
$var reg 1 $ b $end
$var reg 1 % cin $end
$scope module uut $end
$var wire 1 # a $end
$var wire 1 $ b $end
$var wire 1 % cin $end
$var wire 1 " cout $end
$var wire 1 ! s $end
$upscope $end
$upscope $end
$enddefinitions $end
$comment Show the parameter values. $end
$dumpall
$end
#0
$dumpvars
0%
0$
0#
0"
0!
$end
#10000
1"
1!
1%
#20000
0%
1$
#30000
0!
1%
#40000
0"
1!
0%
0$
1#
#50000
0!
1%
#60000
0%
1$
#70000
1"
1!
1%
